README.md
setup.py
charge/__init__.py
charge/time.py
charge/version.py
charge.egg-info/PKG-INFO
charge.egg-info/SOURCES.txt
charge.egg-info/dependency_links.txt
charge.egg-info/requires.txt
charge.egg-info/top_level.txt