Metadata-Version: 1.1
Name: charge
Version: 0.0.1
Summary: classical electrodynamics of charged particle
Home-page: https://github.com/jam31118/charge
Author: sahn
Author-email: jam31118@gmail.com
License: GPLv3
Keywords: physics
Platform: UNKNOWN
Classifier: License :: OSI Approved :: GNU Affero General Public License v3
Classifier: Programming Language :: Python :: 3.5
Classifier: Programming Language :: Python :: 3.6
